{
  "366f47fc-ba78-46ee-b6d2-2a12847fa5dc.png": 96997,
  "about_craft_1.png": 558587,
  "about_craft_2.png": 567614,
  "about_craft_3.png": 463239,
  "admin-login-bg.png": 349791,
  "banner_bond_brothers.png": 469644,
  "banner_bond_friends.png": 525645,
  "banner_bond_husband.png": 403181,
  "banner_bond_mother.png": 444163,
  "banner_bond_sister.png": 496348,
  "banner_bond_wife.png": 502872,
  "banner_daily.png": 403248,
  "banner_elegant_silver.png": 287213,
  "banner_office.png": 506774,
  "banner_party.png": 560471,
  "banner_timeless_rings.png": 428777,
  "best_style_pot_1.png": 558186,
  "best_style_pot_2.png": 552571,
  "beyond_bold_emerald_set.png": 664432,
  "bond_brothers.png": 371607,
  "bond_friends.png": 587954,
  "bond_husband.png": 394077,
  "bond_mother.png": 496475,
  "bond_sister.png": 505447,
  "bond_wife.png": 447408,
  "bridal.png": 509537,
  "categories\\anklets.png": 497230,
  "categories\\bangle.png": 542147,
  "categories\\bracelets.png": 601822,
  "categories\\earrings.png": 515033,
  "categories\\gold_bangle.png": 542147,
  "categories\\gold_bangles_green.png": 707437,
  "categories\\gold_bracelet.png": 601822,
  "categories\\gold_bracelets_green.png": 595547,
  "categories\\gold_earrings_green.png": 403909,
  "categories\\gold_mangalsutra.png": 519788,
  "categories\\gold_mangalsutra_green.png": 541640,
  "categories\\gold_new_arrivals_green.png": 578973,
  "categories\\gold_nosepins_green.png": 424298,
  "categories\\gold_pendants.png": 515033,
  "categories\\gold_pendants_green.png": 460451,
  "categories\\gold_rings_green.png": 370712,
  "categories\\gold_sets_green.png": 504034,
  "categories\\mangalsutra.png": 519788,
  "categories\\mensilver.png": 537308,
  "categories\\newlaunch.png": 537130,
  "categories\\nosepin.png": 558647,
  "categories\\pendants.png": 518605,
  "categories\\perfume.png": 534179,
  "categories\\personalised.png": 529874,
  "categories\\rings.png": 521714,
  "categories\\sets.png": 619496,
  "categories\\silverchains.png": 505578,
  "categories\\toerings.png": 493077,
  "cat_all_nobg-removebg-preview.png": 120537,
  "cat_all_nobg.png": 120537,
  "cat_all_premium.png": 637495,
  "cat_anklets.png": 521860,
  "cat_anklet_wine.png": 271339,
  "cat_bracelets.png": 515025,
  "cat_bracelet_wine.png": 275874,
  "cat_chain_wine.png": 290109,
  "cat_earrings.png": 539831,
  "cat_earrings_wine.png": 211886,
  "cat_men_nobg-removebg-preview.png": 71983,
  "cat_men_nobg.png": 71983,
  "cat_men_premium.png": 533136,
  "cat_pendant.png": 501779,
  "cat_pendant_wine.png": 336858,
  "cat_rings.png": 484258,
  "cat_ring_wine.png": 283708,
  "cat_wedding_bangles.png": 294898,
  "cat_wedding_choker.png": 363733,
  "cat_wedding_diamond.png": 327007,
  "cat_wedding_haram.png": 589692,
  "cat_wedding_mangalsutra.png": 353583,
  "cat_women_nobg-removebg-preview.png": 81221,
  "cat_women_nobg.png": 81221,
  "cat_women_premium.png": 523924,
  "cat_women_premium_nobg.png": 81221,
  "collections\\AstraCollection.png": 82810,
  "collections\\BohoAnklets.png": 74506,
  "collections\\BridalBliss.png": 102052,
  "collections\\cat_family_nobg.png": 120129,
  "collections\\cat_men_nobg.png": 71983,
  "collections\\cat_women_nobg.png": 81788,
  "collections\\DazzlingRings.png": 487172,
  "collections\\SilverClassics.png": 251136,
  "diamond_ring.png": 331389,
  "explore\\classics_banner.png": 442991,
  "explore\\edge_banner.png": 480531,
  "explore\\gold_daily_wear_banner_1775911015640.png": 594455,
  "explore\\gold_office_wear_banner_1775911038204.png": 494368,
  "explore\\iykyk_banner.png": 483977,
  "explore\\thumb_chain.png": 358060,
  "explore\\thumb_pendant.png": 260117,
  "explore\\thumb_ring.png": 215140,
  "f091c310-f56b-4d2d-809a-7c158c723fe2.png": 299036,
  "family_3d_baby.png": 583025,
  "family_3d_brother.png": 540789,
  "family_3d_couple.png": 389568,
  "family_3d_daughter.png": 153099,
  "family_3d_father.png": 353663,
  "family_3d_grandfather.png": 479743,
  "family_3d_grandmother.png": 555896,
  "family_3d_mother.png": 486605,
  "family_3d_sister.png": 544124,
  "family_3d_spouse.png": 437398,
  "family_astra.png": 482726,
  "family_boho.png": 574919,
  "family_curated_classics.png": 438506,
  "family_curated_sisters.png": 586399,
  "family_gift_brother.png": 448010,
  "family_gift_father.png": 353663,
  "family_gift_mother.png": 438506,
  "family_gift_sister.png": 382412,
  "family_hero_banner.jpg": 52780,
  "family_hero_banner_4k.jpg": 105485,
  "family_hero_heirlooms.png": 632479,
  "family_luxury_banner_new.png": 446511,
  "family_price_2999.jpg": 95275,
  "family_price_2999_clean.jpg": 94149,
  "family_price_4999.jpg": 33256,
  "family_price_4999_clean.jpg": 26608,
  "family_price_premium.jpg": 107096,
  "family_price_premium_clean.jpg": 102537,
  "family_promo_jewelry.png": 81221,
  "family_trend_1.png": 482726,
  "family_trend_10.png": 471447,
  "family_trend_2.png": 574919,
  "family_trend_3.png": 438506,
  "family_trend_4.png": 586399,
  "family_trend_5.png": 239065,
  "family_trend_6.png": 377751,
  "family_trend_7.png": 574919,
  "family_trend_8.png": 438506,
  "family_trend_9.png": 509537,
  "family_trend_card_1.jpg": 111849,
  "family_trend_card_4.jpg": 85020,
  "family_wide_banner.png": 528578,
  "family_wide_banner_4k.png": 518774,
  "family_wide_banner_new.png": 492843,
  "gender\\all.png": 564092,
  "gender\\men.png": 378843,
  "gender\\women.png": 415308,
  "gift_baby_silver.png": 583025,
  "gift_bestie_silver.png": 437974,
  "gift_boyfriends.png": 370857,
  "gift_brothers.png": 504142,
  "gift_brother_silver.png": 540789,
  "gift_couples.png": 403673,
  "gift_daughter_silver.png": 153099,
  "gift_friends_silver.png": 547611,
  "gift_gf_silver.png": 446409,
  "gift_grandmother_silver.png": 555896,
  "gift_husbands.png": 424641,
  "gift_husband_silver.png": 308548,
  "gift_mother_silver.png": 486605,
  "gift_sister_silver.png": 544124,
  "gift_wife_silver.png": 437398,
  "glam\\daily_wear.png": 483977,
  "glam\\office_wear.png": 380212,
  "glam\\party_spark.png": 442991,
  "glam\\ritual_range.png": 335564,
  "glam\\wedding_jewels.png": 483518,
  "gold_bangles.png": 431140,
  "gold_color_dual.png": 293991,
  "gold_color_rose.png": 485763,
  "gold_color_white.png": 338732,
  "gold_color_yellow.png": 496973,
  "gold_necklace.png": 498254,
  "gold_trust_badges.png": 151582,
  "haldi.png": 471447,
  "heer_custom_ring.png": 480173,
  "hero\\bridal_gold_campaign.png": 543788,
  "hero\\bridal_royal.png": 613807,
  "hero\\diamond_elegance_campaign.png": 502927,
  "hero\\diamond_luxury.png": 474534,
  "hero\\eternal_diamond_brilliance.png": 343505,
  "hero\\floral_bloom_campaign.png": 530177,
  "hero\\gold_fusion.png": 439075,
  "hero\\hero_bracelets.png": 525185,
  "hero\\hero_masterpiece.png": 432584,
  "hero\\hero_rings.png": 419530,
  "hero\\image.png": 332169,
  "hero\\modern_gold_fusion.png": 374867,
  "hero\\silver_minimalist.png": 428133,
  "hero\\spring_silver_campaign.png": 548228,
  "hero\\sterling_silver_heritage.png": 510047,
  "hero_slide_1.png": 239065,
  "hero_slide_2.png": 377751,
  "hero_slide_3.png": 463239,
  "home_banners\\home_proposal_rings.png": 249787,
  "home_occasions\\home_gift_for_bride.png": 509537,
  "home_occasions\\home_gift_for_bridesmaid.png": 384004,
  "home_occasions\\home_haldi.png": 471447,
  "home_occasions\\home_reception.png": 540403,
  "home_occasions\\home_sangeet.png": 502410,
  "hues\\Gold.png": 59099,
  "hues\\gold_woman.png": 489106,
  "hues\\Oxidised.png": 106002,
  "hues\\oxidised_woman.png": 559659,
  "hues\\RoseGold.png": 51796,
  "hues\\rosegold_woman.png": 522286,
  "hues\\Silver.png": 107434,
  "hues\\silver_woman.png": 527446,
  "images\\celebrate\\women_gift_1.jpg": 43426,
  "images\\celebrate\\women_gift_2.jpg": 71223,
  "images\\collections\\BohoAnklets.jpg": 93434,
  "images\\collections\\BohoAnklets.png": 504503,
  "images\\collections\\BridalBliss.png": 514000,
  "images\\collections\\DazzlingRings.jpg": 38936,
  "images\\collections\\DazzlingRings.png": 537463,
  "images\\collections\\GiftsForHer.png": 408759,
  "images\\collections\\OfficeChic.jpg": 46467,
  "images\\collections\\OfficeChic.png": 414183,
  "images\\collections\\SilverClassics.jpg": 141175,
  "images\\collections\\SilverClassics.png": 495752,
  "images\\hues\\Gold.png": 59099,
  "images\\hues\\Oxidised.png": 106002,
  "images\\hues\\RoseGold.png": 51796,
  "images\\hues\\Silver.png": 107434,
  "images\\men-categories\\bracelets.png": 532594,
  "images\\men-categories\\chains.png": 395288,
  "images\\men-categories\\cufflinks.png": 200470,
  "images\\men-categories\\custom.png": 483507,
  "images\\men-categories\\earrings.png": 572306,
  "images\\men-categories\\pendants.png": 542360,
  "images\\men-categories\\personalised.png": 399457,
  "images\\men-categories\\rings.png": 402683,
  "images\\men-categories\\sets.png": 505028,
  "images\\men-categories\\spiritual.png": 544291,
  "images\\men-gifts\\boyfriends.png": 484717,
  "images\\men-gifts\\brothers.png": 474861,
  "images\\men-gifts\\couples.png": 486680,
  "images\\men-gifts\\husbands.png": 465764,
  "images\\men-hero\\slide1.png": 340609,
  "images\\men-hero\\slide2.png": 278690,
  "images\\men-hero\\slide3.png": 543715,
  "images\\PersonalisedBannerWide.png": 464306,
  "images\\promos\\CoupleRings.png": 143985,
  "images\\promos\\PremiumGifts.png": 72980,
  "InteractiveLook.png": 405554,
  "latest_collections\\glow_banner.png": 400888,
  "latest_collections\\thumb_1.png": 204324,
  "latest_collections\\thumb_2.png": 224645,
  "latest_collections\\thumb_3.png": 375624,
  "latest_collections\\thumb_4.png": 390058,
  "latest_collections\\thumb_5.png": 172330,
  "latest_collections\\thumb_6.png": 249653,
  "latest_collections\\valentine_banner.png": 499341,
  "latest_drop_bracelet.png": 515025,
  "latest_drop_earrings.png": 570970,
  "latest_drop_necklace.png": 501779,
  "latest_drop_ring.png": 505388,
  "lifestyle_casual.png": 555282,
  "lifestyle_date_night.png": 482324,
  "lifestyle_gift_card.png": 567229,
  "lifestyle_minimalistic.png": 553420,
  "lifestyle_party.png": 591221,
  "lifestyle_traditional.png": 589358,
  "lifestyle_twinning.png": 539034,
  "login_hero.png": 442736,
  "login_hero_silver.png": 358490,
  "luxury_gifts_men.png": 409899,
  "luxury_pendant_men.png": 342273,
  "luxury_range_10k.png": 510038,
  "luxury_range_15k.png": 399293,
  "luxury_ring_men.png": 300478,
  "men\\personalized_banner.png": 450125,
  "men\\personalized_full_banner.png": 397664,
  "men\\style_bracelets.png": 483977,
  "men\\style_chains.png": 335564,
  "men\\style_rings.png": 380212,
  "men-interactive.png": 398921,
  "men_bold_look_banner.png": 463064,
  "men_classics_banner.png": 441562,
  "men_edge_banner.png": 328118,
  "men_gift_1.png": 537300,
  "men_gift_2.png": 480709,
  "men_gift_3.png": 502372,
  "men_gift_4.png": 478203,
  "men_hero_bold.png": 548503,
  "men_hero_elite.png": 455055,
  "men_hero_style.png": 444261,
  "men_prod_1.png": 343155,
  "men_prod_2.png": 424139,
  "men_prod_3.png": 437718,
  "men_prod_4.png": 381828,
  "men_prod_bracelet.png": 344719,
  "men_prod_chain.png": 255745,
  "men_prod_pendant.png": 203318,
  "men_prod_ring.png": 319226,
  "men_prod_stud.png": 242756,
  "men_silver_1.png": 378320,
  "men_silver_2.png": 488287,
  "men_silver_3.png": 400580,
  "men_style_1.png": 465502,
  "men_style_2.png": 538239,
  "men_style_3.png": 639934,
  "men_style_4.png": 609861,
  "nav_gift_couple.png": 389568,
  "nav_gift_girls.png": 498238,
  "nav_gift_kids.png": 420472,
  "nav_gift_mens.png": 430874,
  "nav_gift_women.png": 504460,
  "nav_occasion_anniversary.png": 401064,
  "nav_occasion_birthday.png": 526284,
  "nav_occasion_mothers.png": 431460,
  "nav_occasion_valentine.png": 404475,
  "nav_occasion_wedding.png": 605679,
  "new_launch_anklets.png": 521860,
  "new_launch_bracelets.png": 475472,
  "new_launch_chains.png": 508154,
  "new_launch_earrings.png": 312894,
  "new_launch_studs.png": 451196,
  "occasions\\DateNight.png": 552886,
  "occasions\\GirlOuting.png": 552368,
  "occasions\\GotHitched.png": 508911,
  "occasions\\PartyGlam.png": 469791,
  "occasions\\TempleDate.png": 518404,
  "PersonalisedBanner.png": 275438,
  "pink_anklets_1767775536388.png": 521860,
  "pink_bracelets_1767775488371.png": 515025,
  "pink_chains_1767775516641.png": 519554,
  "pink_earrings_1767775466166.png": 570970,
  "premium_bracelet_product.png": 515025,
  "premium_necklace_product.png": 569074,
  "premium_pendant_product.png": 501779,
  "premium_ring_product.png": 505388,
  "price_under_1999.png": 468494,
  "price_under_2999.png": 505999,
  "price_under_3999.png": 427581,
  "price_under_999.png": 488282,
  "products\\gold_earrings.png": 403909,
  "products\\gold_rings.png": 370712,
  "products\\silver_bangles.png": 542147,
  "products\\silver_bracelet.png": 601822,
  "products\\silver_earrings.png": 515033,
  "products\\women\\w1_drop_earrings.png": 659454,
  "prod_earrings_hover.png": 378225,
  "prod_earrings_main.png": 570970,
  "prod_ring_main.png": 505388,
  "promos\\budget_earrings.png": 448155,
  "promos\\budget_pendant.png": 261711,
  "promos\\CoupleRings.png": 143985,
  "promos\\DarkCoupleRings.png": 346955,
  "promos\\DarkPremiumGifts.png": 289438,
  "promos\\PersonalisedBannerWide.png": 249770,
  "promos\\PersonalisedBannerWine.png": 365452,
  "promos\\PremiumGifts.png": 72980,
  "promos\\siblings_day_banner.png": 392754,
  "proposal_banner.png": 249787,
  "proposal_banner_premium.png": 384004,
  "reception.png": 540403,
  "SANDS JEWELS ICON PINK.png": 8995,
  "SANDS JEWELS PINK (1).png": 14882,
  "sands-logo.png": 7627,
  "sands-logoname.png": 12147,
  "sands_gift_card_mockup_1777455722986.png": 415260,
  "sangeet.png": 502410,
  "silver page banner.png": 305290,
  "silver_anklet_dark.png": 275998,
  "silver_anklet_product.png": 159974,
  "silver_bracelet_dark.png": 250720,
  "silver_bracelet_product.png": 147284,
  "silver_chain_dark.png": 356734,
  "silver_chain_product.png": 250463,
  "silver_earrings_dark.png": 388409,
  "silver_earrings_product.png": 109104,
  "soulitaire_emerald_ring.png": 526549,
  "spotlight_silver_hover.png": 569074,
  "spotlight_silver_main.png": 501779,
  "testimonial_customer_1.png": 454968,
  "testimonial_customer_2.png": 503659,
  "testimonial_customer_3.png": 425422,
  "theme_bubbles.png": 392477,
  "theme_drops.png": 373460,
  "theme_infinity.png": 409310,
  "theme_knots.png": 414335,
  "theme_leaves.png": 467460,
  "theme_moon.png": 452851,
  "trending\\ChainLayering.png": 418018,
  "trending\\CuratedCombos.png": 510279,
  "trending\\RingsStacking.png": 431387,
  "trending\\SpiritualPicks.png": 481823,
  "trending_family_3.jpg": 95701,
  "trending_family_4.jpg": 85020,
  "trending_heritage.png": 479743,
  "trending_modern.png": 492431,
  "women-categories\\Bangles.png": 474080,
  "women-categories\\Bracelets.png": 469695,
  "women-categories\\Chains.png": 478633,
  "women-categories\\Earrings.png": 457580,
  "women-categories\\Pendants.png": 552656,
  "women-categories\\Personalised.png": 580114,
  "women-categories\\Rings.png": 496764,
  "women-categories\\Sets.png": 481580,
  "women_hero_radiance.png": 537820
}